mdt/__init__.py
mdt/__version__.py
mdt/configuration.py
mdt/protocols.py
mdt/simulations.py
mdt/utils.py
mdt/cli_scripts/MDT.py
mdt/cli_scripts/__init__.py
mdt/cli_scripts/mdt_apply_mask.py
mdt/cli_scripts/mdt_batch_fit.py
mdt/cli_scripts/mdt_create_bvec_bval.py
mdt/cli_scripts/mdt_create_mask.py
mdt/cli_scripts/mdt_create_protocol.py
mdt/cli_scripts/mdt_create_roi_slice.py
mdt/cli_scripts/mdt_estimate_noise_std.py
mdt/cli_scripts/mdt_get_example_data.py
mdt/cli_scripts/mdt_gui.py
mdt/cli_scripts/mdt_info_img.py
mdt/cli_scripts/mdt_info_protocol.py
mdt/cli_scripts/mdt_init_user_settings.py
mdt/cli_scripts/mdt_list_devices.py
mdt/cli_scripts/mdt_list_models.py
mdt/cli_scripts/mdt_math_img.py
mdt/cli_scripts/mdt_math_protocol.py
mdt/cli_scripts/mdt_model_fit.py
mdt/cli_scripts/mdt_view_maps.py
mdt/cli_scripts/mdt_volume_merge.py
mdt/component_templates/__init__.py
mdt/component_templates/base.py
mdt/component_templates/batch_profiles.py
mdt/component_templates/compartment_models.py
mdt/component_templates/composite_models.py
mdt/component_templates/library_functions.py
mdt/component_templates/parameters.py
mdt/component_templates/utils.py
mdt/data/logo.svg
mdt/data/logo_docs.png
mdt/data/logo_gui.png
mdt/data/mdt.conf
mdt/data/components/standard/batch_profiles/general.py
mdt/data/components/standard/batch_profiles/hcp.py
mdt/data/components/standard/compartment_models/AstroCylinders.py
mdt/data/components/standard/compartment_models/AstroSticks.py
mdt/data/components/standard/compartment_models/Ball.py
mdt/data/components/standard/compartment_models/CHARMEDRestricted.py
mdt/data/components/standard/compartment_models/CylinderGPD.py
mdt/data/components/standard/compartment_models/Dot.py
mdt/data/components/standard/compartment_models/GDRCylinders.py
mdt/data/components/standard/compartment_models/KurtosisTensor.py
mdt/data/components/standard/compartment_models/NODDI.py
mdt/data/components/standard/compartment_models/PDRCylinders.py
mdt-1.2.7.dist-info/LICENSE
mdt-1.2.7.dist-info/METADATA
mdt-1.2.7.dist-info/WHEEL
mdt-1.2.7.dist-info/entry_points.txt
mdt-1.2.7.dist-info/top_level.txt
mdt-1.2.7.dist-info/RECORD
