Metadata-Version: 2.1
Name: mdt
Version: 1.2.7
Summary: Microstructure Diffusion Toolbox
Home-page: https://github.com/robbert-harms/MDT
Author: Robbert Harms
Author-email: robbert@xkls.nl
Maintainer: Robbert Harms
Maintainer-email: robbert@xkls.nl
License: LGPL v3
Keywords: mdt,diffusion MRI,model recovery,imaging analysis
Platform: UNKNOWN
Classifier: Environment :: Console
Classifier: Environment :: X11 Applications :: Qt
Classifier: Intended Audience :: Developers
Classifier: Intended Audience :: Science/Research
Classifier: License :: OSI Approved :: GNU Lesser General Public License v3 or later (LGPLv3+)
Classifier: Development Status :: 5 - Production/Stable
Classifier: Natural Language :: English
Classifier: Operating System :: POSIX :: Linux
Classifier: Operating System :: MacOS :: MacOS X
Classifier: Operating System :: Microsoft :: Windows
Classifier: Programming Language :: Python :: 3
Classifier: Programming Language :: Python :: 3.4
Classifier: Programming Language :: Python :: 3.5
Classifier: Programming Language :: Python :: 3.6
Classifier: Topic :: Scientific/Engineering
License-File: LICENSE
Requires-Dist: argcomplete
Requires-Dist: matplotlib (>=1.5.1)
Requires-Dist: mot (>=0.11.4)
Requires-Dist: nibabel
Requires-Dist: numpy (>=1.9.0)
Requires-Dist: pyopencl (>=2015.2)
Requires-Dist: pyyaml
Requires-Dist: scipy (>=0.12.1)
Requires-Dist: tatsu
